bento/__init__.py
bento/client.py
bento/sim.py
bento/types.py
bento/utils.py
bento/value.py
bento/ecs/__init__.py
bento/ecs/base.py
bento/ecs/graph.py
bento/ecs/grpc.py
bento/example/__init__.py
bento/example/mountcar.py
bento/example/specs.py
bento/graph/__init__.py
bento/graph/analyzers.py
bento/graph/ast.py
bento/graph/compile.py
bento/graph/linters.py
bento/graph/plotter.py
bento/graph/preprocessors.py
bento/graph/transforms.py
bento/graph/value.py
bento/spec/__init__.py
bento/spec/ecs.py
bento/spec/graph.py
bento/spec/sim.py
bentobox-0.1.1.dev13.dist-info/AUTHORS
bentobox-0.1.1.dev13.dist-info/METADATA
bentobox-0.1.1.dev13.dist-info/WHEEL
bentobox-0.1.1.dev13.dist-info/pbr.json
bentobox-0.1.1.dev13.dist-info/top_level.txt
bentobox-0.1.1.dev13.dist-info/RECORD
